sunposition.py
sunposition-1.2.1.dist-info/METADATA
sunposition-1.2.1.dist-info/WHEEL
sunposition-1.2.1.dist-info/entry_points.txt
sunposition-1.2.1.dist-info/licenses/LICENSE
sunposition-1.2.1.dist-info/RECORD
