Metadata-Version: 2.4
Name: sunposition
Version: 1.2.1
Summary: Compute the sun's observed position based on Reda & Adreas's 2004 paper "Solar position algorithm for solar radiation applications"
Project-URL: Homepage, https://github.com/s-bear/sun-position
Author-email: Samuel Powell <samuel.powell@uq.edu.au>
License-Expression: MIT
License-File: LICENSE
Keywords: astronomy,solar,sun
Classifier: Environment :: Console
Classifier: Intended Audience :: Science/Research
Classifier: License :: OSI Approved :: MIT License
Classifier: Programming Language :: Python :: 3
Classifier: Programming Language :: Python :: 3.8
Classifier: Programming Language :: Python :: 3.9
Classifier: Programming Language :: Python :: 3.10
Classifier: Programming Language :: Python :: 3.11
Classifier: Programming Language :: Python :: 3.12
Classifier: Programming Language :: Python :: 3.13
Classifier: Topic :: Scientific/Engineering :: Astronomy
Requires-Python: >=3.8
Requires-Dist: numpy>=1.10
Provides-Extra: jit
Requires-Dist: numba>=0.22; extra == 'jit'
Requires-Dist: scipy; extra == 'jit'
